eth_interceptor/__init__.py
eth_interceptor/cli.py
eth_interceptor/interceptor.py
eth_interceptor/monitor.py
eth_interceptor/submit_tx.py
eth_interceptor/trace.py
eth_transaction_interceptor-1.0.0.dist-info/licenses/LICENSE
eth_transaction_interceptor-1.0.0.dist-info/METADATA
eth_transaction_interceptor-1.0.0.dist-info/WHEEL
eth_transaction_interceptor-1.0.0.dist-info/entry_points.txt
eth_transaction_interceptor-1.0.0.dist-info/top_level.txt
eth_transaction_interceptor-1.0.0.dist-info/RECORD
