Metadata-Version: 2.4
Name: eth-transaction-interceptor
Version: 1.0.0
Summary: Advanced transaction interceptor and simulator for Ethereum
Home-page: https://github.com/nerolation/eth-transaction-interceptor
Author: Toni Wahrstätter
Author-email: Toni Wahrstätter <info@toniwahrstaetter.com>
License: MIT
Project-URL: Homepage, https://github.com/nerolation/eth-transaction-interceptor
Project-URL: Documentation, https://github.com/nerolation/eth-transaction-interceptor/tree/main/docs
Project-URL: Repository, https://github.com/nerolation/eth-transaction-interceptor
Project-URL: Bug Tracker, https://github.com/nerolation/eth-transaction-interceptor/issues
Keywords: ethereum,web3,transaction,interceptor,simulator,blockchain,defi
Classifier: Development Status :: 4 - Beta
Classifier: Intended Audience :: Developers
Classifier: Topic :: Software Development :: Libraries :: Python Modules
Classifier: Topic :: System :: Monitoring
Classifier: Topic :: Software Development :: Testing
Classifier: Topic :: Internet :: WWW/HTTP :: Dynamic Content
Classifier: License :: OSI Approved :: MIT License
Classifier: Programming Language :: Python :: 3
Classifier: Programming Language :: Python :: 3.8
Classifier: Programming Language :: Python :: 3.9
Classifier: Programming Language :: Python :: 3.10
Classifier: Programming Language :: Python :: 3.11
Classifier: Programming Language :: Python :: 3.12
Classifier: Operating System :: OS Independent
Classifier: Environment :: Console
Requires-Python: >=3.8
License-File: LICENSE
Requires-Dist: web3>=6.0.0
Requires-Dist: eth-account>=0.10.0
Requires-Dist: eth-utils>=4.0.0
Requires-Dist: flask>=3.0.0
Requires-Dist: requests>=2.31.0
Requires-Dist: colorama>=0.4.6
Requires-Dist: odfpy>=1.4.1
Requires-Dist: rlp>=3.0.0
Provides-Extra: dev
Requires-Dist: pytest>=7.0.0; extra == "dev"
Requires-Dist: pytest-cov>=4.0.0; extra == "dev"
Requires-Dist: black>=23.0.0; extra == "dev"
Requires-Dist: flake8>=6.0.0; extra == "dev"
Requires-Dist: mypy>=1.0.0; extra == "dev"
Requires-Dist: twine>=4.0.0; extra == "dev"
Requires-Dist: build>=0.10.0; extra == "dev"
Dynamic: author
Dynamic: home-page
Dynamic: license-file
Dynamic: requires-python
